kalabash_admin_limits/__init__.py
kalabash_admin_limits/app_settings.py
kalabash_admin_limits/controls.py
kalabash_admin_limits/forms.py
kalabash_admin_limits/general_callbacks.py
kalabash_admin_limits/kalmonak_extension.py
kalabash_admin_limits/lib.py
kalabash_admin_limits/models.py
kalabash_admin_limits/tests.py
kalabash_admin_limits/urls.py
kalabash_admin_limits/views.py
kalabash_admin_limits/locale/en/LC_MESSAGES/django.mo
kalabash_admin_limits/locale/en/LC_MESSAGES/django.po
kalabash_admin_limits/locale/fr/LC_MESSAGES/django.mo
kalabash_admin_limits/locale/fr/LC_MESSAGES/django.po
kalabash_admin_limits/migrations/0001_initial.py
kalabash_admin_limits/migrations/__init__.py
kalabash_admin_limits/templates/kalabash_admin_limits/poolusage.html
kalabash_admin_limits-1.0.5.dist-info/LICENSE
kalabash_admin_limits-1.0.5.dist-info/METADATA
kalabash_admin_limits-1.0.5.dist-info/WHEEL
kalabash_admin_limits-1.0.5.dist-info/top_level.txt
kalabash_admin_limits-1.0.5.dist-info/RECORD
